historicity/__init__.py
historicity-0.1.0.dist-info/DESCRIPTION.rst
historicity-0.1.0.dist-info/METADATA
historicity-0.1.0.dist-info/RECORD
historicity-0.1.0.dist-info/WHEEL
historicity-0.1.0.dist-info/metadata.json
historicity-0.1.0.dist-info/top_level.txt
