Metadata-Version: 2.0
Name: historicity
Version: 0.1.0
Summary: historical authenticity
Home-page: https://github.com/rmorshea/historicity
Author: Ryan Morshead
Author-email: ryan.morshead@gmail.com
License: UNKNOWN
Platform: UNKNOWN
Classifier: Intended Audience :: Developers
Classifier: Intended Audience :: System Administrators
Classifier: Intended Audience :: Science/Research
Classifier: License :: OSI Approved :: MIT License
Classifier: Programming Language :: Python
Classifier: Programming Language :: Python :: 3.4
Classifier: Programming Language :: Python :: 3.5
Classifier: Programming Language :: Python :: 3.6
Requires-Python: >=2.7
